senseiv2/__init__.py
senseiv2/inference.py
senseiv2/models.py
senseiv2/train.py
senseiv2/utils.py
senseiv2/data/__init__.py
senseiv2/data/dataset.py
senseiv2/data/sliding_window.py
senseiv2/data/transforms.py
senseiv2_test-1.0.dist-info/LICENSE
senseiv2_test-1.0.dist-info/METADATA
senseiv2_test-1.0.dist-info/WHEEL
senseiv2_test-1.0.dist-info/top_level.txt
senseiv2_test-1.0.dist-info/RECORD
