Metadata-Version: 2.1
Name: senseiv2-test
Version: 1.0
Summary: Sensor Independent Cloud and Shadow Masking with Partial Labels and Multimodal Inputs
Author: Alistair Francis
Author-email: Alistair Francis <alistair.m.francis@gmail.com>
Project-URL: Homepage, https://github.com/aliFrancis/SEnSeIv2
Project-URL: Issues, https://github.com/aliFrancis/SEnSeIv2/issues
Classifier: Programming Language :: Python :: 3
Classifier: License :: OSI Approved :: GNU General Public License v3 (GPLv3)
Classifier: Operating System :: OS Independent
Requires-Python: >=3.9
License-File: LICENSE
